{
  "horses": [
    {
      "horse_number": 5,
      "name": "セイウンデセオ",
      "popularity": 2,
      "odds": 5.1,
      "mark": "○",
      "score": 110.86,
      "track_aptitude": 1,
      "total_points": 87.14,
      "detail_points": {
        "score": 50.0,
        "bias": 10.95,
        "pace": 10.2,
        "3f": 9.0,
        "margin": 6.0,
        "track": 0.99
      },
      "avg_margin": 0.9650000000000001,
      "race_name": "福島9R",
      "pred_prob_won": 0.22227796018123627,
      "pred_prob_in_top2": 0.1582424372434616,
      "pred_prob_in_top3": 0.5042556166648865,
      "score_z": 1.6412838584975578,
      "上り3F平均": 36.0,
      "Ave-3F平均": 35.57,
      "PCI平均": 48.96,
      "-3F差平均": 0.75,
      "想定脚質": "中団",
      "track_bias_aptitude_score": 64.3,
      "investment_value_score": 99.1,
      "total_investment_index": 86.5,
      "investment_rating": 0.9879796308279037,
      "stability_score": 75,
      "investment_mark": "◎"
    },
    {
      "horse_number": 7,
      "name": "スターウェーブ",
      "popularity": 3,
      "odds": 6.0,
      "mark": "◎",
      "score": 104.6,
      "track_aptitude": 0,
      "total_points": 87.37661915930002,
      "detail_points": {
        "score": 47.17661915930002,
        "bias": 15.0,
        "pace": 10.2,
        "3f": 9.0,
        "margin": 6.0,
        "track": 0.0
      },
      "avg_margin": 0.625,
      "race_name": "福島9R",
      "pred_prob_won": 0.14724478423595427,
      "pred_prob_in_top2": 0.1303076595067978,
      "pred_prob_in_top3": 0.40260212421417235,
      "score_z": 1.0602103032474715,
      "上り3F平均": 34.5,
      "Ave-3F平均": 36.69,
      "PCI平均": 56.45,
      "-3F差平均": 0.35,
      "想定脚質": "先行",
      "track_bias_aptitude_score": 76.6,
      "investment_value_score": 80.1,
      "total_investment_index": 77.8,
      "investment_rating": 0.8493676471710205,
      "stability_score": 75,
      "investment_mark": "○"
    },
    {
      "horse_number": 10,
      "name": "ハッピーサプライズ",
      "popularity": 5,
      "odds": 17.8,
      "mark": "▲",
      "score": 96.78,
      "track_aptitude": 0,
      "total_points": 77.79964820494317,
      "detail_points": {
        "score": 43.64964820494317,
        "bias": 10.95,
        "pace": 10.2,
        "3f": 9.0,
        "margin": 4.0,
        "track": 0.0
      },
      "avg_margin": 1.145,
      "race_name": "福島9R",
      "pred_prob_won": 0.06821360290050507,
      "pred_prob_in_top2": 0.08186554908752441,
      "pred_prob_in_top3": 0.23525906205177308,
      "score_z": 0.33433247544305167,
      "上り3F平均": 35.41,
      "Ave-3F平均": 35.54,
      "PCI平均": 50.45,
      "-3F差平均": 0.8,
      "想定脚質": "中団",
      "track_bias_aptitude_score": 56.6,
      "investment_value_score": 51.5,
      "total_investment_index": 53.4,
      "investment_rating": 0.40571759164333343,
      "stability_score": 60,
      "investment_mark": "△"
    },
    {
      "horse_number": 6,
      "name": "ノーブルオリンポス",
      "popularity": 4,
      "odds": 11.2,
      "mark": "△",
      "score": 99.64,
      "track_aptitude": 0,
      "total_points": 71.1695634133141,
      "detail_points": {
        "score": 44.93956341331409,
        "bias": 4.95,
        "pace": 8.28,
        "3f": 9.0,
        "margin": 4.0,
        "track": 0.0
      },
      "avg_margin": 2.0,
      "race_name": "福島9R",
      "pred_prob_won": 0.07337542176246643,
      "pred_prob_in_top2": 0.07423298805952072,
      "pred_prob_in_top3": 0.24630171954631805,
      "score_z": 0.5998069751259982,
      "上り3F平均": 36.06,
      "Ave-3F平均": 36.0,
      "PCI平均": 49.78,
      "-3F差平均": 1.72,
      "想定脚質": "後方",
      "track_bias_aptitude_score": 1,
      "investment_value_score": 59.0,
      "total_investment_index": 41.7,
      "investment_rating": 0.37215213611722003,
      "stability_score": 60,
      "investment_mark": "△"
    },
    {
      "horse_number": 4,
      "name": "ラトルシェ",
      "popularity": 1,
      "odds": 1.7,
      "mark": "▲",
      "score": 102.11,
      "track_aptitude": 2,
      "total_points": 84.2135810932708,
      "detail_points": {
        "score": 46.05358109327079,
        "bias": 10.95,
        "pace": 10.2,
        "3f": 9.0,
        "margin": 6.0,
        "track": 2.0100000000000002
      },
      "avg_margin": 0.7583333333333334,
      "race_name": "福島9R",
      "pred_prob_won": 0.11861505508422851,
      "pred_prob_in_top2": 0.1008087232708931,
      "pred_prob_in_top3": 0.3261178195476532,
      "score_z": 0.8290804066703611,
      "上り3F平均": 36.22,
      "Ave-3F平均": 34.46,
      "PCI平均": 45.32,
      "-3F差平均": 0.42,
      "想定脚質": "中団",
      "track_bias_aptitude_score": 72.1,
      "investment_value_score": 100,
      "total_investment_index": 88.0,
      "investment_rating": 0.31529454886913294,
      "stability_score": 75,
      "investment_mark": "☆"
    },
    {
      "horse_number": 2,
      "name": "ウイントールキン",
      "popularity": 7,
      "odds": 23.6,
      "mark": "△",
      "score": 95.92,
      "track_aptitude": 0,
      "total_points": 77.41177160382465,
      "detail_points": {
        "score": 43.26177160382464,
        "bias": 10.95,
        "pace": 10.2,
        "3f": 9.0,
        "margin": 4.0,
        "track": 0.0
      },
      "avg_margin": 1.2600000000000002,
      "race_name": "福島9R",
      "pred_prob_won": 0.04100106358528137,
      "pred_prob_in_top2": 0.0681049183011055,
      "pred_prob_in_top3": 0.17041225135326385,
      "score_z": 0.2545044790348929,
      "上り3F平均": 34.05,
      "Ave-3F平均": 36.0,
      "PCI平均": 44.54,
      "-3F差平均": 0.72,
      "想定脚質": "中団",
      "track_bias_aptitude_score": 56.6,
      "investment_value_score": 36.1,
      "total_investment_index": 44.1,
      "investment_rating": 0.1883910578489303,
      "stability_score": 60,
      "investment_mark": "☆"
    },
    {
      "horse_number": 11,
      "name": "クリノゴッホ",
      "popularity": 10,
      "odds": 38.1,
      "mark": "△",
      "score": 81.31,
      "track_aptitude": 1,
      "total_points": 68.81237957784593,
      "detail_points": {
        "score": 36.67237957784593,
        "bias": 10.95,
        "pace": 10.2,
        "3f": 9.0,
        "margin": 1.0,
        "track": 0.99
      },
      "avg_margin": 4.050000000000001,
      "race_name": "福島9R",
      "pred_prob_won": 0.02012918293476105,
      "pred_prob_in_top2": 0.024453450366854666,
      "pred_prob_in_top3": 0.08389018476009369,
      "score_z": -1.101643227387432,
      "上り3F平均": 31.47,
      "Ave-3F平均": 35.12,
      "PCI平均": 48.61,
      "-3F差平均": 0.79,
      "想定脚質": "中団",
      "track_bias_aptitude_score": 64.3,
      "investment_value_score": 9.1,
      "total_investment_index": 27.9,
      "investment_rating": -0.325018123537302,
      "stability_score": 30,
      "investment_mark": "××"
    },
    {
      "horse_number": 3,
      "name": "ブラヴィーノ",
      "popularity": 9,
      "odds": 37.1,
      "mark": "×",
      "score": 86.77,
      "track_aptitude": 0,
      "total_points": 65.36494497564496,
      "detail_points": {
        "score": 39.134944975644956,
        "bias": 4.95,
        "pace": 8.28,
        "3f": 7.0,
        "margin": 6.0,
        "track": 0.0
      },
      "avg_margin": 1.0,
      "race_name": "福島9R",
      "pred_prob_won": 0.01618104912340641,
      "pred_prob_in_top2": 0.02354302741587162,
      "pred_prob_in_top3": 0.07213053703308106,
      "score_z": -0.5948282734472619,
      "上り3F平均": 34.7,
      "Ave-3F平均": 35.1,
      "PCI平均": 51.23,
      "-3F差平均": 0.98,
      "想定脚質": "後方",
      "track_bias_aptitude_score": 1,
      "investment_value_score": 9.5,
      "total_investment_index": 10.0,
      "investment_rating": -0.4022992944717407,
      "stability_score": 75,
      "investment_mark": "××"
    },
    {
      "horse_number": 9,
      "name": "ツィスカリーゼ",
      "popularity": 8,
      "odds": 34.2,
      "mark": "×",
      "score": 84.29,
      "track_aptitude": 2,
      "total_points": 63.17641710265199,
      "detail_points": {
        "score": 38.01641710265199,
        "bias": 4.95,
        "pace": 10.2,
        "3f": 4.0,
        "margin": 4.0,
        "track": 2.0100000000000002
      },
      "avg_margin": 1.8199999999999998,
      "race_name": "福島9R",
      "pred_prob_won": 0.014876185916364193,
      "pred_prob_in_top2": 0.021261686459183693,
      "pred_prob_in_top3": 0.07002245783805847,
      "score_z": -0.8250299375079978,
      "上り3F平均": 36.38,
      "Ave-3F平均": 35.7,
      "PCI平均": 48.32,
      "-3F差平均": 0.92,
      "想定脚質": "逃げ",
      "track_bias_aptitude_score": 25.8,
      "investment_value_score": 10.7,
      "total_investment_index": 17.8,
      "investment_rating": -0.4053573927283287,
      "stability_score": 60,
      "investment_mark": "××"
    },
    {
      "horse_number": 1,
      "name": "コムーネ",
      "popularity": 6,
      "odds": 21.5,
      "mark": "×",
      "score": 85.48,
      "track_aptitude": 0,
      "total_points": 62.70313007396717,
      "detail_points": {
        "score": 38.55313007396717,
        "bias": 4.95,
        "pace": 10.2,
        "3f": 5.0,
        "margin": 4.0,
        "track": 0.0
      },
      "avg_margin": 1.4555555555555555,
      "race_name": "福島9R",
      "pred_prob_won": 0.01635936927050352,
      "pred_prob_in_top2": 0.021444617956876754,
      "pred_prob_in_top3": 0.06391983851790428,
      "score_z": -0.7145702680594993,
      "上り3F平均": 36.12,
      "Ave-3F平均": 35.09,
      "PCI平均": 47.23,
      "-3F差平均": 0.78,
      "想定脚質": "逃げ",
      "track_bias_aptitude_score": 10.2,
      "investment_value_score": 15.0,
      "total_investment_index": 15.9,
      "investment_rating": -0.4144208477810025,
      "stability_score": 60,
      "investment_mark": "××"
    },
    {
      "horse_number": 8,
      "name": "マルモリディライト",
      "popularity": 11,
      "odds": 63.9,
      "mark": "△",
      "score": 77.2,
      "track_aptitude": 2,
      "total_points": 70.97869023994228,
      "detail_points": {
        "score": 34.81869023994227,
        "bias": 10.95,
        "pace": 10.2,
        "3f": 9.0,
        "margin": 4.0,
        "track": 2.0100000000000002
      },
      "avg_margin": 1.215,
      "race_name": "福島9R",
      "pred_prob_won": 0.013829508237540722,
      "pred_prob_in_top2": 0.021553538739681244,
      "pred_prob_in_top3": 0.06349489912390709,
      "score_z": -1.483146791617121,
      "上り3F平均": 34.88,
      "Ave-3F平均": 34.63,
      "PCI平均": 49.37,
      "-3F差平均": 0.72,
      "想定脚質": "中団",
      "track_bias_aptitude_score": 72.1,
      "investment_value_score": 1,
      "total_investment_index": 24.8,
      "investment_rating": -0.49204080700874336,
      "stability_score": 60,
      "investment_mark": "消"
    }
  ]
}